tests/__init__.py
tests/quick_test.py
tests/test_unify_llm.py
tests/test_unify_llm_tool.py
unify_llm_tool/__init__.py
unify_llm_tool/connections/__init__.py
unify_llm_tool/tools/__init__.py
unify_llm_tool/tools/benchmark_llm_tool.py
unify_llm_tool/tools/chat_tool.py
unify_llm_tool/tools/optimize_llm_tool.py
unify_llm_tool/tools/single_sign_on_tool.py
unify_llm_tool/tools/unifypf.py
unify_llm_tool/tools/utils.py
unify_llm_tool/yamls/benchmark_llm_tool.yaml
unify_llm_tool/yamls/chat_tool.yaml
unify_llm_tool/yamls/optimize_llm_tool.yaml
unify_llm_tool/yamls/single_sign_on_tool.yaml
unify_integration-0.1.11.dist-info/LICENSE
unify_integration-0.1.11.dist-info/METADATA
unify_integration-0.1.11.dist-info/WHEEL
unify_integration-0.1.11.dist-info/entry_points.txt
unify_integration-0.1.11.dist-info/top_level.txt
unify_integration-0.1.11.dist-info/RECORD
