Metadata-Version: 2.1
Name: unify_integration
Version: 0.1.11
Summary: The Unify tool package gives access to a single sign on client with multiple LLM endpoints and their metadata
Author: Kato Steven, Omkar Khade
Author-email: Kacper Kozdon <k.kozdon@gmail.com>
Project-URL: Homepage, https://github.com/Kacper-W-Kozdon/promptflow_unify_integration
Project-URL: Issues, https://github.com/Kacper-W-Kozdon/promptflow_unify_integration/issues
Classifier: Programming Language :: Python :: 3
Classifier: License :: OSI Approved :: MIT License
Classifier: Operating System :: OS Independent
Requires-Python: >=3.8
License-File: LICENSE
Provides-Extra: build
Requires-Dist: promptflow ; extra == 'build'
Requires-Dist: unifyai ; extra == 'build'
Provides-Extra: dev
Requires-Dist: requests-mock ; extra == 'dev'
Requires-Dist: python-dotenv ; extra == 'dev'
